{
  "data": [
    {
      "id": "1",
      "rol": "Diseño"
    },
    {
      "id": "2",
      "rol": "TIC"
    },
    {
      "id": "3",
      "rol": "Editor"
    },
    {
      "id": "4",
      "rol": "Coordinador"
    },
    {
      "id": "5",
      "rol": "Docente"
    },
    {
      "id": "6",
      "rol": "Directivo de colegio"
    },
    {
      "id": "7",
      "rol": "Directivo o administrador de red de colegios"
    },
    {
      "id": "8",
      "rol": "Profesional educador"
    }
  ]
}